Metadata-Version: 1.0
Name: jselect
Version: 0.0.0.3
Summary: A tools that helps you to select data from json file
Home-page: https://github.com/lennon-guan/jselect
Author: guan ming
Author-email: i@guanming.me
License: UNKNOWN
Platform: UNKNOWN
